{"affected_prs":["https://github.com/openvinotoolkit/openvino/pull/35283"],"category":"Code Issue","count":2,"first_seen":"2026-06-09T12:29:17Z","last_seen":"2026-06-09T12:44:43Z","recent_run_urls":["https://github.com/openvinotoolkit/openvino/actions/runs/27196482346"],"recent_timestamps":["2026-06-09T12:44:43Z","2026-06-09T12:29:17Z"],"signature":"error: cannot convert 'ov::op::internal::DynamicQuantize::OutputStorageType' to 'cldnn::data_types'|Build / Build|Code Issue","title":"GPU dynamic_quantize unit test fails to compile after target-branch merge"}